MANIFEST.in
README.md
requirements.txt
setup.cfg
setup.py
embed/__init__.py
embed/configs.py
embed/embed.py
embed/exceptions.py
embed/image.py
embed/regex.py
embed/request.py
embed/thread.py
embed/url.py
embed/utils.py
embed/parsers/__init__.py
embed/parsers/amazon.py
embed/parsers/facebook.py
embed/parsers/generic.py
embed/parsers/instagram.py
embed/parsers/soundcloud.py
embed/parsers/twitter.py
embed/parsers/vimeo.py
embed/parsers/youtube.py
embed_python.egg-info/PKG-INFO
embed_python.egg-info/SOURCES.txt
embed_python.egg-info/dependency_links.txt
embed_python.egg-info/requires.txt
embed_python.egg-info/top_level.txt