Metadata-Version: 1.1
Name: embed-python
Version: 0.1.12
Summary: A simple python library to scrape any URL and return the most meaningful data from it
Home-page: https://github.com/thoughtchimp/embed-python
Author: Thought Chimp
Author-email: whoop@thoughtchimp.com
License: MIT
Keywords: embed,scrapper,oembed,scrape,crawl
Platform: UNKNOWN
Classifier: Development Status :: 4 - Beta
Classifier: Intended Audience :: Developers
Classifier: Operating System :: OS Independent
Classifier: Programming Language :: Python :: 3.5
Classifier: Operating System :: OS Independent
Classifier: Topic :: Software Development :: Libraries :: Python Modules
